raggify/__init__.py
raggify/cli/__init__.py
raggify/cli/cli.py
raggify/config/__init__.py
raggify/config/config_manager.py
raggify/config/document_store_config.py
raggify/config/embed_config.py
raggify/config/general_config.py
raggify/config/ingest_cache_config.py
raggify/config/ingest_config.py
raggify/config/llm_config.py
raggify/config/pipeline_config.py
raggify/config/rerank_config.py
raggify/config/retrieve_config.py
raggify/config/vector_store_config.py
raggify/core/__init__.py
raggify/core/const.py
raggify/core/event.py
raggify/core/exts.py
raggify/core/metadata.py
raggify/core/utils.py
raggify/document_store/__init__.py
raggify/document_store/document_store.py
raggify/document_store/document_store_manager.py
raggify/embed/__init__.py
raggify/embed/embed.py
raggify/embed/embed_manager.py
raggify/ingest/__init__.py
raggify/ingest/ingest.py
raggify/ingest/loader/__init__.py
raggify/ingest/loader/base_loader.py
raggify/ingest/loader/file_loader.py
raggify/ingest/loader/file_reader/__init__.py
raggify/ingest/loader/file_reader/audio_reader.py
raggify/ingest/loader/file_reader/dummy_media_reader.py
raggify/ingest/loader/file_reader/html_reader.py
raggify/ingest/loader/file_reader/pdf_reader.py
raggify/ingest/loader/file_reader/video_reader.py
raggify/ingest/loader/util.py
raggify/ingest/loader/web_page_loader.py
raggify/ingest/loader/web_page_reader/__init__.py
raggify/ingest/loader/web_page_reader/base_web_page_reader.py
raggify/ingest/loader/web_page_reader/default_web_page_reader.py
raggify/ingest/loader/web_page_reader/wikipedia_reader.py
raggify/ingest/parser.py
raggify/ingest/transform/__init__.py
raggify/ingest/transform/base_transform.py
raggify/ingest/transform/caption_transform.py
raggify/ingest/transform/embed_transform.py
raggify/ingest/transform/media_split_transform.py
raggify/ingest/transform/meta_transform.py
raggify/ingest/upsert.py
raggify/ingest/util.py
raggify/ingest_cache/__init__.py
raggify/ingest_cache/ingest_cache.py
raggify-0.3.3.dist-info/WHEEL
raggify-0.3.3.dist-info/entry_points.txt
raggify-0.3.3.dist-info/METADATA
raggify-0.3.3.dist-info/RECORD
