Metadata-Version: 2.3
Name: raggify
Version: 0.3.3
Summary: llama index based library for building multimodal RAG systems
Keywords: rag,multimodal,embedding,cli,fastapi,streamlit,typer
Author: jun76
Author-email: jun76 <jun76.git@gmail.com>
License: MIT License
Classifier: Development Status :: 4 - Beta
Classifier: Intended Audience :: Developers
Classifier: Intended Audience :: System Administrators
Classifier: License :: OSI Approved :: MIT License
Classifier: Operating System :: OS Independent
Classifier: Programming Language :: Python :: 3
Classifier: Topic :: System :: Systems Administration
Classifier: Topic :: Utilities
Requires-Dist: aiofiles
Requires-Dist: chromadb
Requires-Dist: docx2txt
Requires-Dist: fastapi
Requires-Dist: fastapi-mcp
Requires-Dist: ipython
Requires-Dist: llama-cloud-services
Requires-Dist: llama-index-embeddings-openai
Requires-Dist: llama-index==0.14.10
Requires-Dist: llama-index-core==0.14.10
Requires-Dist: llama-index-readers-file
Requires-Dist: llama-index-readers-web
Requires-Dist: llama-index-readers-wikipedia
Requires-Dist: llama-index-retrievers-bm25
Requires-Dist: llama-index-vector-stores-chroma
Requires-Dist: mashumaro
Requires-Dist: nbconvert
Requires-Dist: pydantic
Requires-Dist: pydantic-settings
Requires-Dist: python-dotenv
Requires-Dist: python-multipart
Requires-Dist: raggify-client
Requires-Dist: requests
Requires-Dist: typer
Requires-Dist: uvicorn[standard]
Requires-Dist: wikipedia
Requires-Dist: flagembedding ; extra == 'all'
Requires-Dist: ffmpeg-python ; extra == 'all'
Requires-Dist: llama-index-embeddings-bedrock ; extra == 'all'
Requires-Dist: llama-index-embeddings-clip ; extra == 'all'
Requires-Dist: llama-index-embeddings-cohere ; extra == 'all'
Requires-Dist: llama-index-embeddings-huggingface ; extra == 'all'
Requires-Dist: llama-index-embeddings-voyageai ; extra == 'all'
Requires-Dist: llama-index-llms-huggingface==0.6.1 ; extra == 'all'
Requires-Dist: llama-index-postprocessor-cohere-rerank ; extra == 'all'
Requires-Dist: llama-index-postprocessor-flag-embedding-reranker ; extra == 'all'
Requires-Dist: llama-index-postprocessor-voyageai-rerank ; extra == 'all'
Requires-Dist: llama-index-storage-docstore-postgres ; extra == 'all'
Requires-Dist: llama-index-storage-docstore-redis ; extra == 'all'
Requires-Dist: llama-index-storage-kvstore-postgres ; extra == 'all'
Requires-Dist: llama-index-storage-kvstore-redis ; extra == 'all'
Requires-Dist: llama-index-vector-stores-postgres ; extra == 'all'
Requires-Dist: llama-index-vector-stores-redis ; extra == 'all'
Requires-Dist: openai-agents ; extra == 'all'
Requires-Dist: psycopg2-binary ; extra == 'all'
Requires-Dist: pytest ; extra == 'all'
Requires-Dist: pytest-cov ; extra == 'all'
Requires-Dist: pymupdf ; extra == 'all'
Requires-Dist: datasets>=2.20.0 ; extra == 'all'
Requires-Dist: sentence-transformers>=5.2.0 ; extra == 'all'
Requires-Dist: soundfile ; extra == 'all'
Requires-Dist: streamlit ; extra == 'all'
Requires-Dist: torch==2.9.0 ; extra == 'all'
Requires-Dist: torchaudio==2.9.0 ; extra == 'all'
Requires-Dist: torchvision==0.24.0 ; extra == 'all'
Requires-Dist: transformers ; extra == 'all'
Requires-Dist: ffmpeg-python ; extra == 'audio'
Requires-Dist: llama-index-embeddings-bedrock ; extra == 'audio'
Requires-Dist: pytest ; extra == 'dev'
Requires-Dist: pytest-cov ; extra == 'dev'
Requires-Dist: openai-agents ; extra == 'exam'
Requires-Dist: streamlit ; extra == 'exam'
Requires-Dist: llama-index-embeddings-bedrock ; extra == 'image'
Requires-Dist: llama-index-embeddings-cohere ; extra == 'image'
Requires-Dist: llama-index-embeddings-voyageai ; extra == 'image'
Requires-Dist: pymupdf ; extra == 'image'
Requires-Dist: flagembedding ; extra == 'localmodel'
Requires-Dist: llama-index-embeddings-clip ; extra == 'localmodel'
Requires-Dist: llama-index-embeddings-huggingface ; extra == 'localmodel'
Requires-Dist: llama-index-llms-huggingface==0.6.1 ; extra == 'localmodel'
Requires-Dist: llama-index-postprocessor-flag-embedding-reranker ; extra == 'localmodel'
Requires-Dist: datasets>=2.20.0 ; extra == 'localmodel'
Requires-Dist: sentence-transformers>=5.2.0 ; extra == 'localmodel'
Requires-Dist: soundfile ; extra == 'localmodel'
Requires-Dist: torch==2.9.0 ; extra == 'localmodel'
Requires-Dist: torchaudio==2.9.0 ; extra == 'localmodel'
Requires-Dist: torchvision==0.24.0 ; extra == 'localmodel'
Requires-Dist: transformers ; extra == 'localmodel'
Requires-Dist: llama-index-storage-docstore-postgres ; extra == 'postgres'
Requires-Dist: llama-index-storage-kvstore-postgres ; extra == 'postgres'
Requires-Dist: llama-index-vector-stores-postgres ; extra == 'postgres'
Requires-Dist: psycopg2-binary ; extra == 'postgres'
Requires-Dist: llama-index-storage-docstore-redis ; extra == 'redis'
Requires-Dist: llama-index-storage-kvstore-redis ; extra == 'redis'
Requires-Dist: llama-index-vector-stores-redis ; extra == 'redis'
Requires-Dist: llama-index-postprocessor-cohere-rerank ; extra == 'rerank'
Requires-Dist: llama-index-postprocessor-voyageai-rerank ; extra == 'rerank'
Requires-Dist: llama-index-embeddings-bedrock ; extra == 'text'
Requires-Dist: llama-index-embeddings-cohere ; extra == 'text'
Requires-Dist: llama-index-embeddings-voyageai ; extra == 'text'
Requires-Dist: ffmpeg-python ; extra == 'video'
Requires-Dist: llama-index-embeddings-bedrock ; extra == 'video'
Requires-Python: >=3.10
Project-URL: Homepage, https://github.com/jun76/raggify
Project-URL: Issues, https://github.com/jun76/raggify/issues
Provides-Extra: all
Provides-Extra: audio
Provides-Extra: dev
Provides-Extra: exam
Provides-Extra: image
Provides-Extra: localmodel
Provides-Extra: postgres
Provides-Extra: redis
Provides-Extra: rerank
Provides-Extra: text
Provides-Extra: video
